{"gameObjects":[{"Position":{"angle":0,"x":169,"y":461},"RectangleCollider":{"Position":{"angle":0,"x":169,"y":461},"height":50,"width":50},"objectType":1},{"Position":{"angle":0,"x":564,"y":269},"RectangleCollider":{"Position":{"angle":0,"x":564,"y":269},"height":50,"width":50},"objectType":1},{"Position":{"angle":0,"x":100,"y":184},"RectangleCollider":{"Position":{"angle":0,"x":100,"y":184},"height":50,"width":50},"objectType":1},{"CircleCollider":{"Position":{"angle":0,"x":539,"y":484},"radius":50},"Position":{"angle":0,"x":539,"y":484},"RectangleCollider":{"Position":{"angle":0,"x":100,"y":184},"height":50,"width":50},"Robot":{"rotationAngle":6.212404481856e-312,"speed":6.212404481856e-312},"objectType":2},{"CircleCollider":{"Position":{"angle":0,"x":443,"y":572},"radius":50},"Position":{"angle":0,"x":443,"y":572},"RectangleCollider":{"Position":{"angle":0,"x":100,"y":184},"height":50,"width":50},"Robot":{"rotationAngle":6.196227713344e-312,"speed":2.520930999667e-311},"objectType":2},{"CircleCollider":{"Position":{"angle":0,"x":226,"y":316},"radius":50},"ControlledRobot":{"rotationDirection":0,"speedDirection":0},"Position":{"angle":0,"x":226,"y":316},"RectangleCollider":{"Position":{"angle":0,"x":100,"y":184},"height":50,"width":50},"Robot":{"rotationAngle":6.21244578511e-312,"speed":6.21244578037e-312},"objectType":3}],"height":0,"width":0}